{
    "fields": [
        "国家",
        "KFC数量",
        "X_COORD",
        "Y_COORD"
    ],
    "rows": [
        {
            "国家": "美国",
            "KFC数量": "49975",
            "X_COORD": "-77.0364",
            "Y_COORD": "38.89517"
        },
        {
            "国家": "日本",
            "KFC数量": "26344",
            "X_COORD": "139.809189",
            "Y_COORD": "35.683056"
        },
        {
            "国家": "印度",
            "KFC数量": "20860",
            "X_COORD": "77.216751",
            "Y_COORD": "28.568726"
        },
        {
            "国家": "印度尼西亚",
            "KFC数量": "18107",
            "X_COORD": "106.762467",
            "Y_COORD": "-6.293904"
        },
        {
            "国家": "英国",
            "KFC数量": "11292",
            "X_COORD": "-0.128014",
            "Y_COORD": "51.508158"
        },
        {
            "国家": "马来西亚",
            "KFC数量": "7713",
            "X_COORD": "101.707672",
            "Y_COORD": "3.15021"
        },
        {
            "国家": "澳大利亚",
            "KFC数量": "7085",
            "X_COORD": "149.12439",
            "Y_COORD": "-35.320862"
        },
        {
            "国家": "加拿大",
            "KFC数量": "6033",
            "X_COORD": "-75.697403",
            "Y_COORD": "45.395096"
        },
        {
            "国家": "意大利",
            "KFC数量": "3337",
            "X_COORD": "12.487712",
            "Y_COORD": "41.902264"
        },
        {
            "国家": "韩国",
            "KFC数量": "3019",
            "X_COORD": "126.977961",
            "Y_COORD": "37.566589"
        },
        {
            "国家": "法国",
            "KFC数量": "2944",
            "X_COORD": "2.35839",
            "Y_COORD": "48.860324"
        },
        {
            "国家": "德国",
            "KFC数量": "2940",
            "X_COORD": "13.387741",
            "Y_COORD": "52.505379"
        },
        {
            "国家": "巴西",
            "KFC数量": "2935",
            "X_COORD": "-47.929214",
            "Y_COORD": "-15.780102"
        },
        {
            "国家": "西班牙",
            "KFC数量": "2926",
            "X_COORD": "-3.696312",
            "Y_COORD": "40.428955"
        },
        {
            "国家": "菲律宾",
            "KFC数量": "2656",
            "X_COORD": "120.985535",
            "Y_COORD": "14.632355"
        },
        {
            "国家": "泰国",
            "KFC数量": "1978",
            "X_COORD": "100.552666",
            "Y_COORD": "13.745571"
        },
        {
            "国家": "新加坡",
            "KFC数量": "1803",
            "X_COORD": "103.821319",
            "Y_COORD": "1.304812"
        },
        {
            "国家": "墨西哥",
            "KFC数量": "1690",
            "X_COORD": "-99.134087",
            "Y_COORD": "19.406433"
        },
        {
            "国家": "荷兰",
            "KFC数量": "1645",
            "X_COORD": "4.868457",
            "Y_COORD": "52.366066"
        },
        {
            "国家": "俄罗斯",
            "KFC数量": "1546",
            "X_COORD": "37.676598",
            "Y_COORD": "55.782085"
        }
    ]
}